kong/__init__.py
kong/acls.py
kong/certificates.py
kong/cli.py
kong/client.py
kong/components.py
kong/consumers.py
kong/plugins.py
kong/routes.py
kong/services.py
kong/snis.py
kong/utils.py
kong_incubator-0.4.9.dist-info/LICENSE
kong_incubator-0.4.9.dist-info/METADATA
kong_incubator-0.4.9.dist-info/WHEEL
kong_incubator-0.4.9.dist-info/entry_points.txt
kong_incubator-0.4.9.dist-info/top_level.txt
kong_incubator-0.4.9.dist-info/RECORD
