Metadata-Version: 2.1
Name: kong-incubator
Version: 0.4.9
Summary: Declare and manage Kong resources with yaml
Home-page: https://github.com/asyrjasalo/kongman
Author: Anssi Syrjäsalo (aio-kong by Luca Sbardella)
Author-email: anssi.syrjasalo@gmail.com
License: BSD License
Keywords: kong admin yaml configuration async cli
Platform: any
Classifier: Development Status :: 3 - Alpha
Classifier: Intended Audience :: Developers
Classifier: Intended Audience :: System Administrators
Classifier: License :: OSI Approved :: BSD License
Classifier: Operating System :: OS Independent
Classifier: Programming Language :: Python
Classifier: Programming Language :: Python :: 3 :: Only
Classifier: Programming Language :: Python :: 3.6
Classifier: Programming Language :: Python :: 3.7
Classifier: Topic :: Utilities
Requires-Dist: aiohttp
Requires-Dist: click
Requires-Dist: pyyaml
